Metadata-Version: 2.4
Name: keyrings.google-artifactregistry-auth-gdplabs
Version: 1.1.3
Summary: Keyring backend for Google Auth tokens for GDPLabs
Home-page: https://github.com/GoogleCloudPlatform/artifact-registry-python-tools
Author: Megan Kuo
Author-email: megankuo@google.com
Classifier: Development Status :: 5 - Production/Stable
Classifier: Intended Audience :: Developers
Classifier: License :: OSI Approved :: Apache Software License
Classifier: Programming Language :: Python :: 3
Classifier: Programming Language :: Python :: 3 :: Only
Requires-Python: >=3.6
License-File: LICENSE
Requires-Dist: keyring
Requires-Dist: google-auth
Requires-Dist: pluggy
Provides-Extra: tox
Requires-Dist: tox; extra == "tox"
Provides-Extra: testing
Requires-Dist: pytest!=3.7.3,>=3.5; extra == "testing"
Requires-Dist: pytest-checkdocs>=1.2.3; extra == "testing"
Requires-Dist: pytest-flake8; extra == "testing"
Requires-Dist: pytest-black>=0.3.7; platform_python_implementation != "PyPy" and extra == "testing"
Requires-Dist: pytest-cov; extra == "testing"
Requires-Dist: pytest-mypy; platform_python_implementation != "PyPy" and extra == "testing"
Dynamic: license-file
